vmtconnect/__about__.py
vmtconnect/__init__.py
vmtconnect/command_line.py
vmtconnect/security.py
vmtconnect/util.py
vmtconnect/versions.py
vmtconnect-3.6.2.dist-info/LICENSE
vmtconnect-3.6.2.dist-info/METADATA
vmtconnect-3.6.2.dist-info/WHEEL
vmtconnect-3.6.2.dist-info/entry_points.txt
vmtconnect-3.6.2.dist-info/top_level.txt
vmtconnect-3.6.2.dist-info/RECORD
