Metadata-Version: 2.1
Name: vmtconnect
Version: 3.6.2
Summary: Turbonomic API Client
Home-page: https://github.com/turbonomic/vmt-connect
Author: Turbonomic Inc.
Author-email: ray.mileo@ibm.com
License: Apache 2.0
Classifier: Intended Audience :: Developers
Classifier: License :: OSI Approved :: Apache Software License
Classifier: Operating System :: OS Independent
Classifier: Programming Language :: Python :: 3
Classifier: Topic :: Software Development
Requires-Python: >=3.6
License-File: LICENSE
Requires-Dist: cryptography (<4,>=3)
Requires-Dist: ijson (<4,>=3.1.4)
Requires-Dist: requests (<3,>=2.25.1)
